ansys/scade/almgw_msoffice/__init__.py
ansys/scade/almgw_msoffice/almgw_msoffice.properties
ansys/scade/almgw_msoffice/almgw_msoffice.srg
ansys/scade/almgw_msoffice/almgw_msoffice23r1.srg
ansys/scade/almgw_msoffice/almgw_msoffice24r1.srg
ansys/scade/almgw_msoffice/msexcel.py
ansys/scade/almgw_msoffice/msoffice.py
ansys/scade/almgw_msoffice/msword.py
ansys/scade/almgw_msoffice/reggitext2.ps1
ansys/scade/almgw_msoffice/register.py
ansys/scade/almgw_msoffice/settings.py
ansys/scade/almgw_msoffice/setup.py
ansys/scade/almgw_msoffice/trace.py
ansys/scade/almgw_msoffice/unregister.py
ansys/scade/almgw_msoffice/utils.py
ansys/scade/almgw_msoffice/res/msword.bmp
ansys/scade/almgw_msoffice/res/word-select.ps1
ansys_scade_almgw_msoffice-3.1.1.dist-info/entry_points.txt
ansys_scade_almgw_msoffice-3.1.1.dist-info/LICENSE
ansys_scade_almgw_msoffice-3.1.1.dist-info/WHEEL
ansys_scade_almgw_msoffice-3.1.1.dist-info/METADATA
ansys_scade_almgw_msoffice-3.1.1.dist-info/RECORD
