Metadata-Version: 2.3
Name: ansys-scade-almgw-msoffice
Version: 3.1.1
Summary: Ansys SCADE ALM Gateway connector for MS-Office
Keywords: Scade,LifeCycle,ALM gateway
Author-email: "ANSYS, Inc." <pyansys.core@ansys.com>
Maintainer-email: "ANSYS, Inc." <pyansys.core@ansys.com>
Requires-Python: >=3.7,!=3.8.*,!=3.9.*,<3.11
Classifier: Development Status :: 4 - Beta
Classifier: Programming Language :: Python :: 3.7
Classifier: Programming Language :: Python :: 3.10
Classifier: License :: OSI Approved :: MIT License
Classifier: Operating System :: Microsoft :: Windows
Requires-Dist: importlib-metadata >= 1.0; python_version < '3.8'
Requires-Dist: importlib-metadata >= 4.0; python_version >= '3.8'
Requires-Dist: ansys-scade-pyalmgw
Requires-Dist: lxml
Requires-Dist: python-docx
Requires-Dist: xlsxwriter
Requires-Dist: build==1.2.2.post1 ; extra == "build"
Requires-Dist: twine==6.1.0 ; extra == "build"
Requires-Dist: ansys-sphinx-theme[autoapi]==1.3.2 ; extra == "doc"
Requires-Dist: jupyter_sphinx==0.5.3 ; extra == "doc"
Requires-Dist: nbsphinx==0.9.6 ; extra == "doc"
Requires-Dist: sphinx==8.1.3 ; extra == "doc"
Requires-Dist: sphinx-autodoc-typehints==3.0.1 ; extra == "doc"
Requires-Dist: sphinxcontrib-globalsubs==0.1.2 ; extra == "doc"
Requires-Dist: sphinxcontrib-httpdomain==1.8.1 ; extra == "doc"
Requires-Dist: sphinx-copybutton==0.5.2 ; extra == "doc"
Requires-Dist: pytest >= 8.3.4 ; extra == "tests" and ( python_version >= '3.8')
Requires-Dist: pytest <= 7.4.4 ; extra == "tests" and ( python_version < '3.8')
Requires-Dist: pytest-cov >= 6.0.0 ; extra == "tests" and ( python_version >= '3.8')
Requires-Dist: pytest-cov <= 4.1.0 ; extra == "tests" and ( python_version < '3.8')
Requires-Dist: ansys-scade-apitools ; extra == "tests"
Requires-Dist: pyparsing ; extra == "tests"
Project-URL: discussions, https://github.com/ansys/scade-almgw-msoffice/discussions
Project-URL: documentation, https://almgw-msoffice.scade.docs.pyansys.com
Project-URL: homepage, https://www.ansys.com/products/embedded-software/ansys-scade-suite
Project-URL: issues, https://github.com/ansys/scade-almgw-msoffice/issues
Project-URL: releases, https://github.com/ansys/scade-almgw-msoffice/releases
Project-URL: source, https://github.com/ansys/scade-almgw-msoffice
Provides-Extra: build
Provides-Extra: doc
Provides-Extra: tests
